Metadata-Version: 2.1
Name: lyseum-hack-ege-client
Version: 1.0.0
Summary: UNKNOWN
Home-page: https://pypi.org/project/lyseum_hack_ege_client/
Author: grin-de-vald1
Author-email: grin-de-vald1@ya.ru
License: MIT
Keywords: hack lyseum client yandex-proxy
Platform: UNKNOWN
